sphinx_seepln_theme/__init__.py
sphinx_seepln_theme/breadcrumbs.html
sphinx_seepln_theme/footer.html
sphinx_seepln_theme/gfooter.html
sphinx_seepln_theme/header.html
sphinx_seepln_theme/layout.html
sphinx_seepln_theme/search.html
sphinx_seepln_theme/searchbox.html
sphinx_seepln_theme/side.html
sphinx_seepln_theme/theme.conf
sphinx_seepln_theme/tools.html
sphinx_seepln_theme/static/css/badge_only.css
sphinx_seepln_theme/static/css/readthedocs-doc-embed.css
sphinx_seepln_theme/static/css/theme.css
sphinx_seepln_theme/static/js/readthedocs-analytics.js
sphinx_seepln_theme/static/js/readthedocs-doc-embed.js
sphinx_seepln_theme/static/js/theme.edc90ee605ed3d8dcdff.js
sphinx_seepln_theme-1.0.18.dist-info/LICENSE
sphinx_seepln_theme-1.0.18.dist-info/METADATA
sphinx_seepln_theme-1.0.18.dist-info/WHEEL
sphinx_seepln_theme-1.0.18.dist-info/entry_points.txt
sphinx_seepln_theme-1.0.18.dist-info/top_level.txt
sphinx_seepln_theme-1.0.18.dist-info/RECORD
